yuning_util/__init__.py
yuning_util/dev_mode.py
yutility/__init__.py
yutility/dev_mode.py
yutility/log.py
yutility-0.6.3.dist-info/LICENSE
yutility-0.6.3.dist-info/METADATA
yutility-0.6.3.dist-info/WHEEL
yutility-0.6.3.dist-info/top_level.txt
yutility-0.6.3.dist-info/RECORD
