Metadata-Version: 2.1
Name: yutility
Version: 0.6.3
Summary: Utility functions for development
Home-page: https://github.com/ynshen/yutility/
Author: Yuning Shen
Author-email: ynshen23@gmail.com
License: UNKNOWN
Project-URL: Bug Reports, https://github.com/ynshen/yutility/issues/
Project-URL: Source, https://github.com/ynshen/yutility/
Keywords: development utility
Platform: UNKNOWN
Classifier: License :: OSI Approved :: MIT License
Requires-Python: >=3.5
